{
  "code": "BH",
  "name": "Cmsn for Pres of America'S Heritage Abrd",
  "employees": 18,
  "avgSalary": 10844,
  "topOccupations": [
    {
      "name": "Miscellaneous Administration and Program",
      "count": 18,
      "avgSalary": 10844
    }
  ],
  "topStates": [
    {
      "name": "District of Columbia",
      "code": "DC",
      "count": 18
    }
  ],
  "education": [
    {
      "level": "NO FORMAL EDUCATION OR SOME ELEMENTARY SCHOOL - DID NOT COMPLETE",
      "count": 11
    },
    {
      "level": "HIGH SCHOOL GRADUATE OR CERTIFICATE OF EQUIVALENCY",
      "count": 7
    }
  ]
}