{"code": "HS", "name": "Department of Homeland Security", "employees": 227584, "avgSalary": 118849, "topOccupations": [{"name": "Emergency Management Specialist", "count": 10697, "avgSalary": 93352}, {"name": "Management and Program Analysis", "count": 8081, "avgSalary": 136994}, {"name": "Miscellaneous Administration and Program", "count": 6943, "avgSalary": 118958}, {"name": "Information Technology Management", "count": 5008, "avgSalary": 142328}, {"name": "Human Resources Management", "count": 1860, "avgSalary": 119464}, {"name": "Security Administration", "count": 1666, "avgSalary": 127683}, {"name": "General Attorney", "count": 1619, "avgSalary": 167744}, {"name": "Program Management", "count": 1509, "avgSalary": 176896}, {"name": "Contracting", "count": 1242, "avgSalary": 136923}, {"name": "Financial Administration and Program", "count": 962, "avgSalary": 123789}, {"name": "Security Clerical and Assistance", "count": 954, "avgSalary": 79594}, {"name": "Environmental Protection Specialist", "count": 829, "avgSalary": 99508}, {"name": "Supply Program Management", "count": 822, "avgSalary": 75856}, {"name": "Training Instruction", "count": 724, "avgSalary": 114885}, {"name": "Logistics Management", "count": 626, "avgSalary": 120173}], "topStates": [{"name": "District of Columbia", "code": "DC", "count": 13735}, {"name": "Virginia", "code": "VA", "count": 7991}, {"name": "Texas", "code": "TX", "count": 4273}, {"name": "Maryland", "code": "MD", "count": 4200}, {"name": "California", "code": "CA", "count": 2678}, {"name": "Florida", "code": "FL", "count": 2643}, {"name": "No Data Reported", "code": "NDR", "count": 2465}, {"name": "Georgia", "code": "GA", "count": 2284}, {"name": "New York", "code": "NY", "count": 1412}, {"name": "North Carolina", "code": "NC", "count": 1263}, {"name": "Missouri", "code": "MO", "count": 1003}, {"name": "Massachusetts", "code": "MA", "count": 812}, {"name": "Washington", "code": "WA", "count": 810}, {"name": "Louisiana", "code": "LA", "count": 809}, {"name": "New Jersey", "code": "NJ", "count": 791}], "education": [{"level": "High School Graduate Or Certificate of Equivalency", "count": 76992}, {"level": "Bachelor's Degree", "count": 59443}, {"level": "Master's Degree", "count": 19910}, {"level": "Some College - Less Than One Year", "count": 15490}, {"level": "Associate Degree", "count": 12473}, {"level": "One Year College", "count": 8660}, {"level": "Two Years College", "count": 8562}, {"level": "No Formal Education Or Some Elementary School - Did Not Complete", "count": 5443}, {"level": "First Professional", "count": 4179}, {"level": "Three Years College", "count": 3912}, {"level": "Four Years College", "count": 3806}, {"level": "Doctorate Degree", "count": 2237}, {"level": "Post-bachelor's", "count": 2217}, {"level": "Terminal Occupational Program - Certificate of Completion, Diploma Or Equivalent", "count": 1752}, {"level": "Terminal Occupational Program - Did Not Complete", "count": 725}, {"level": "Invalid", "count": 632}, {"level": "Post-master's", "count": 346}, {"level": "Some High School - Did Not Complete", "count": 345}, {"level": "Post-first Professional", "count": 227}, {"level": "Sixth-year Degree", "count": 85}, {"level": "Post-doctorate", "count": 74}, {"level": "Post-sixth Year", "count": 40}, {"level": "No Data Reported", "count": 20}, {"level": "Elementary School Completed - No High School", "count": 14}]}