{"code": "SB", "name": "Transfer Out (Mass)", "description": "Mass transfers between agencies due to reorganization", "totalCount": 14532, "monthlyTrend": [{"month": "201910", "count": 12}, {"month": "201911", "count": 20}, {"month": "201912", "count": 13}, {"month": "202001", "count": 19}, {"month": "202002", "count": 44}, {"month": "202003", "count": 13}, {"month": "202004", "count": 22}, {"month": "202005", "count": 14}, {"month": "202006", "count": 12}, {"month": "202007", "count": 17}, {"month": "202008", "count": 23}, {"month": "202009", "count": 56}, {"month": "202010", "count": 943}, {"month": "202011", "count": 12}, {"month": "202012", "count": 15}, {"month": "202101", "count": 35}, {"month": "202102", "count": 24}, {"month": "202103", "count": 26}, {"month": "202104", "count": 21}, {"month": "202105", "count": 22}, {"month": "202106", "count": 19}, {"month": "202107", "count": 39}, {"month": "202108", "count": 31}, {"month": "202109", "count": 21}, {"month": "202110", "count": 12}, {"month": "202111", "count": 23}, {"month": "202112", "count": 27}, {"month": "202201", "count": 31}, {"month": "202202", "count": 16}, {"month": "202203", "count": 19}, {"month": "202204", "count": 19}, {"month": "202205", "count": 611}, {"month": "202206", "count": 35}, {"month": "202207", "count": 4024}, {"month": "202208", "count": 3858}, {"month": "202209", "count": 3540}, {"month": "202210", "count": 300}, {"month": "202211", "count": 19}, {"month": "202212", "count": 27}, {"month": "202301", "count": 33}, {"month": "202302", "count": 19}, {"month": "202303", "count": 24}, {"month": "202304", "count": 25}, {"month": "202305", "count": 21}, {"month": "202306", "count": 31}, {"month": "202307", "count": 27}, {"month": "202308", "count": 18}, {"month": "202309", "count": 22}, {"month": "202310", "count": 24}, {"month": "202311", "count": 13}, {"month": "202312", "count": 20}, {"month": "202401", "count": 20}, {"month": "202402", "count": 16}, {"month": "202403", "count": 10}, {"month": "202404", "count": 12}, {"month": "202405", "count": 14}, {"month": "202406", "count": 12}, {"month": "202407", "count": 11}, {"month": "202408", "count": 15}, {"month": "202409", "count": 12}, {"month": "202410", "count": 14}, {"month": "202411", "count": 12}, {"month": "202412", "count": 10}, {"month": "202501", "count": 20}, {"month": "202502", "count": 5}, {"month": "202503", "count": 1}, {"month": "202504", "count": 3}, {"month": "202505", "count": 3}, {"month": "202506", "count": 4}, {"month": "202507", "count": 7}, {"month": "202508", "count": 3}, {"month": "202509", "count": 5}, {"month": "202510", "count": 6}, {"month": "202511", "count": 6}], "topAgencies": [{"code": "NV", "name": "DEPARTMENT OF THE NAVY", "count": 8266}, {"code": "AF", "name": "DEPARTMENT OF THE AIR FORCE", "count": 4014}, {"code": "DD", "name": "DEPARTMENT OF DEFENSE", "count": 1012}, {"code": "AG", "name": "Department of Agriculture", "count": 260}, {"code": "VA", "name": "Department of Veterans Affairs", "count": 257}, {"code": "IN", "name": "Department of Interior", "count": 183}, {"code": "DJ", "name": "Department of Justice", "count": 174}, {"code": "HS", "name": "Department of Homeland Security", "count": 58}, {"code": "AR", "name": "DEPARTMENT OF THE ARMY", "count": 52}, {"code": "HE", "name": "Department of Health and Human Services", "count": 52}, {"code": "OM", "name": "Office of Personnel Management", "count": 35}, {"code": "AM", "name": "U.s. Agency for International Dev", "count": 27}, {"code": "ED", "name": "Department of Education", "count": 21}, {"code": "SZ", "name": "Social Security Administration", "count": 17}, {"code": "GS", "name": "General Services Administration", "count": 16}, {"code": "GW", "name": "Inter Bound and Water Comm U.s. Section", "count": 13}, {"code": "CM", "name": "Department of Commerce", "count": 11}, {"code": "TD", "name": "Department of Transportation", "count": 11}, {"code": "DN", "name": "Department of Energy", "count": 6}, {"code": "SE", "name": "Securities and Exchange Commission", "count": 6}], "topOccupations": [{"name": "MISCELLANEOUS ADMINISTRATION AND PROGRAM", "count": 19}, {"name": "HUMAN RESOURCES MANAGEMENT", "count": 17}, {"name": "MANAGEMENT AND PROGRAM ANALYSIS", "count": 14}, {"name": "CORRECTIONAL OFFICER", "count": 11}, {"name": "CONTRACTING", "count": 10}, {"name": "GENERAL ATTORNEY", "count": 10}, {"name": "GENERAL BUSINESS AND INDUSTRY", "count": 9}, {"name": "MISCELLANEOUS CLERK AND ASSISTANT", "count": 9}, {"name": "VETERANS CLAIMS EXAMINING", "count": 9}, {"name": "SOCIAL SCIENCE", "count": 7}, {"name": "GENERAL NATURAL RESOURCES MANAGEMENT AND BIOLOGICAL SCIENCES", "count": 5}, {"name": "NURSE", "count": 5}, {"name": "GRANTS MANAGEMENT", "count": 5}, {"name": "SECURITY ADMINISTRATION", "count": 4}, {"name": "INFORMATION TECHNOLOGY MANAGEMENT", "count": 4}, {"name": "GENERAL INSPECTION, INVESTIGATION, ENFORCEMENT, AND COMPLIANCE SERIES", "count": 4}, {"name": "SECRETARY", "count": 4}, {"name": "FINANCIAL ADMINISTRATION AND PROGRAM", "count": 4}, {"name": "PARK RANGER", "count": 4}, {"name": "WILDLAND FIRE MANAGEMENT", "count": 4}], "byAge": [{"label": "20-24", "count": 4}, {"label": "25-29", "count": 22}, {"label": "30-34", "count": 39}, {"label": "35-39", "count": 54}, {"label": "40-44", "count": 54}, {"label": "45-49", "count": 37}, {"label": "50-54", "count": 24}, {"label": "55-59", "count": 30}, {"label": "60-64", "count": 12}, {"label": "65 OR MORE", "count": 2}], "avgSalaryAtSeparation": 77042, "avgLOS": 10.3}