{"code": "0482", "name": "FISH BIOLOGY", "group": "BIOLOGICAL SCIENCES GROUP", "employees": 1714, "avgSalary": 114482, "topAgencies": [{"code": "IN", "name": "DEPARTMENT OF INTERIOR", "count": 774, "avgSalary": 104843}, {"code": "CM", "name": "DEPARTMENT OF COMMERCE", "count": 605, "avgSalary": 132353}, {"code": "AG", "name": "DEPARTMENT OF AGRICULTURE", "count": 220, "avgSalary": 95520}, {"code": "AR", "name": "DEPARTMENT OF THE ARMY", "count": 72, "avgSalary": 0}, {"code": "DN", "name": "DEPARTMENT OF ENERGY", "count": 37, "avgSalary": 134099}, {"code": "EP", "name": "ENVIRONMENTAL PROTECTION AGENCY", "count": 4, "avgSalary": 138354}, {"code": "NV", "name": "DEPARTMENT OF THE NAVY", "count": 2, "avgSalary": 0}], "topStates": [{"state": "WA", "count": 293}, {"state": "CA", "count": 179}, {"state": "OR", "count": 135}, {"state": "AK", "count": 95}, {"state": "MA", "count": 81}, {"state": "FL", "count": 75}, {"state": "MI", "count": 70}, {"state": "WI", "count": 61}, {"state": "ID", "count": 50}, {"state": "MT", "count": 42}, {"state": "CO", "count": 34}, {"state": "MO", "count": 32}, {"state": "AZ", "count": 30}, {"state": "MS", "count": 29}, {"state": "NV", "count": 28}], "ageDistribution": [{"label": "20-24", "count": 2}, {"label": "25-29", "count": 34}, {"label": "30-34", "count": 158}, {"label": "35-39", "count": 219}, {"label": "40-44", "count": 256}, {"label": "45-49", "count": 302}, {"label": "50-54", "count": 304}, {"label": "55-59", "count": 241}, {"label": "60-64", "count": 131}, {"label": "65 OR MORE", "count": 67}], "educationDistribution": [{"label": "BACHELOR'S DEGREE", "count": 560}, {"label": "MASTER'S DEGREE", "count": 539}, {"label": "DOCTORATE DEGREE", "count": 298}, {"label": "POST-DOCTORATE", "count": 80}, {"label": "POST-BACHELOR'S", "count": 69}, {"label": "HIGH SCHOOL GRADUATE OR CERTIFICATE OF EQUIVALENCY", "count": 62}, {"label": "POST-MASTER'S", "count": 41}, {"label": "FOUR YEARS COLLEGE", "count": 18}, {"label": "THREE YEARS COLLEGE", "count": 11}, {"label": "ASSOCIATE DEGREE", "count": 8}, {"label": "TWO YEARS COLLEGE", "count": 7}, {"label": "FIRST PROFESSIONAL", "count": 6}, {"label": "POST-SIXTH YEAR", "count": 6}, {"label": "POST-FIRST PROFESSIONAL", "count": 3}, {"label": "SOME COLLEGE - LESS THAN ONE YEAR", "count": 3}, {"label": "ONE YEAR COLLEGE", "count": 2}, {"label": "NO DATA REPORTED", "count": 1}], "salaryByGrade": [{"grade": "GS-11", "count": 401, "avgSalary": 88166}, {"grade": "ZP-03", "count": 318, "avgSalary": 114468}, {"grade": "GS-12", "count": 275, "avgSalary": 106441}, {"grade": "ZP-04", "count": 212, "avgSalary": 164396}, {"grade": "GS-13", "count": 200, "avgSalary": 131226}, {"grade": "GS-09", "count": 140, "avgSalary": 70411}, {"grade": "GS-14", "count": 60, "avgSalary": 157574}, {"grade": "ZP-02", "count": 56, "avgSalary": 89502}, {"grade": "GS-15", "count": 23, "avgSalary": 182961}, {"grade": "ZP-05", "count": 14, "avgSalary": 193554}, {"grade": "GS-07", "count": 5, "avgSalary": 53667}, {"grade": "ST-00", "count": 3, "avgSalary": 214092}, {"grade": "ES-00", "count": 3, "avgSalary": 215832}, {"grade": "EF-00", "count": 1, "avgSalary": 104350}, {"grade": "DB-04", "count": 1, "avgSalary": 0}, {"grade": "DB-02", "count": 1, "avgSalary": 0}, {"grade": "ND-04", "count": 1, "avgSalary": 0}]}